autodidaqt_receiver/__init__.py
autodidaqt_receiver/fixtures/nano_xps/.zattrs
autodidaqt_receiver/fixtures/nano_xps/.zgroup
autodidaqt_receiver/fixtures/nano_xps/.zmetadata
autodidaqt_receiver/fixtures/nano_xps/__xarray_dataarray_variable__/.zarray
autodidaqt_receiver/fixtures/nano_xps/__xarray_dataarray_variable__/.zattrs
autodidaqt_receiver/fixtures/nano_xps/__xarray_dataarray_variable__/0.0.0
autodidaqt_receiver/fixtures/nano_xps/__xarray_dataarray_variable__/0.1.0
autodidaqt_receiver/fixtures/nano_xps/__xarray_dataarray_variable__/1.0.0
autodidaqt_receiver/fixtures/nano_xps/__xarray_dataarray_variable__/1.1.0
autodidaqt_receiver/fixtures/nano_xps/alpha/.zarray
autodidaqt_receiver/fixtures/nano_xps/alpha/.zattrs
autodidaqt_receiver/fixtures/nano_xps/alpha/0
autodidaqt_receiver/fixtures/nano_xps/beta/.zarray
autodidaqt_receiver/fixtures/nano_xps/beta/.zattrs
autodidaqt_receiver/fixtures/nano_xps/beta/0
autodidaqt_receiver/fixtures/nano_xps/chi/.zarray
autodidaqt_receiver/fixtures/nano_xps/chi/.zattrs
autodidaqt_receiver/fixtures/nano_xps/chi/0
autodidaqt_receiver/fixtures/nano_xps/eV/.zarray
autodidaqt_receiver/fixtures/nano_xps/eV/.zattrs
autodidaqt_receiver/fixtures/nano_xps/eV/0
autodidaqt_receiver/fixtures/nano_xps/hv/.zarray
autodidaqt_receiver/fixtures/nano_xps/hv/.zattrs
autodidaqt_receiver/fixtures/nano_xps/hv/0
autodidaqt_receiver/fixtures/nano_xps/psi/.zarray
autodidaqt_receiver/fixtures/nano_xps/psi/.zattrs
autodidaqt_receiver/fixtures/nano_xps/psi/0
autodidaqt_receiver/fixtures/nano_xps/theta/.zarray
autodidaqt_receiver/fixtures/nano_xps/theta/.zattrs
autodidaqt_receiver/fixtures/nano_xps/theta/0
autodidaqt_receiver/fixtures/nano_xps/x/.zarray
autodidaqt_receiver/fixtures/nano_xps/x/.zattrs
autodidaqt_receiver/fixtures/nano_xps/x/0
autodidaqt_receiver/fixtures/nano_xps/y/.zarray
autodidaqt_receiver/fixtures/nano_xps/y/.zattrs
autodidaqt_receiver/fixtures/nano_xps/y/0
autodidaqt_receiver/fixtures/nano_xps/z/.zarray
autodidaqt_receiver-1.1.0.dist-info/LICENSE.txt
autodidaqt_receiver-1.1.0.dist-info/WHEEL
autodidaqt_receiver-1.1.0.dist-info/METADATA
autodidaqt_receiver-1.1.0.dist-info/RECORD
