Metadata-Version: 2.1
Name: autodidaqt-receiver
Version: 1.1.0
Summary: Analyis-side bridge for autodiDAQt.
Home-page: https://github.com/chstan/autodidaqt-receiver
License: GNU GPL v3.0
Keywords: data acquisition,physics,instrumentation,DAQ
Author: chstan
Author-email: chstansbury@gmail.com
Requires-Python: >=3.8,<3.10
Classifier: Intended Audience :: Developers
Classifier: Intended Audience :: Science/Research
Classifier: License :: OSI Approved :: GNU General Public License v3 or later (GPLv3+)
Classifier: License :: Other/Proprietary License
Classifier: Natural Language :: English
Classifier: Operating System :: OS Independent
Classifier: Programming Language :: Python :: 3
Classifier: Programming Language :: Python :: 3.8
Classifier: Programming Language :: Python :: 3.9
Classifier: Topic :: Scientific/Engineering
Classifier: Topic :: Scientific/Engineering :: Physics
Classifier: Topic :: Software Development :: Libraries :: Python Modules
Requires-Dist: autodidaqt-common (>=0.1.0,<0.2.0)
Requires-Dist: matplotlib (>=3.1.1,<4.0.0)
Requires-Dist: numpy (>=1.20,<2.0)
Requires-Dist: pandas (>=1.2.4,<2.0.0)
Requires-Dist: ptpython (>=3.0.19,<4.0.0)
Requires-Dist: pynng (>=0.7.1,<0.8.0)
Requires-Dist: scipy (>=1.7.1,<2.0.0)
Requires-Dist: xarray (>=0.18.2,<0.19.0)
Requires-Dist: zarr (>=2.8.3,<3.0.0)
Project-URL: Repository, https://github.com/chstan/autodidaqt-receiver
